binlorry/binlorry.py
binlorry/misc.py
binlorry/version.py
binlorry-1.3.1.dist-info/LICENSE
binlorry-1.3.1.dist-info/METADATA
binlorry-1.3.1.dist-info/WHEEL
binlorry-1.3.1.dist-info/entry_points.txt
binlorry-1.3.1.dist-info/top_level.txt
binlorry-1.3.1.dist-info/RECORD
