Metadata-Version: 2.1
Name: binlorry
Version: 1.3.1
Summary: BinLorry: a flexible tool for binning and filtering sequencing reads
Home-page: http://github.com/rambaut/binlorry
Author: Andrew Rambaut and Aine O Toole
Author-email: a.rambaut@ed.ac.uk
License: GPL
Platform: UNKNOWN
